{"assets":{"93C48EF3C6BA71FE6A02681D2F3B7885":{"type":"texture","index":261,"assetRequest":{"type":"slide","state":"contents","slide":"A78F63D5-FDA3-4B1D-88CB-7B8DFFCEED2E"},"url":{"web":"assets/93C48EF3C6BA71FE6A02681D2F3B7885.svg"},"width":748,"height":45},"0A1D444013DA9E1178F2E33F32ADF646":{"type":"texture","index":264,"assetRequest":{"type":"slide","state":"outgoing","slide":"A78F63D5-FDA3-4B1D-88CB-7B8DFFCEED2E"},"url":{"web":"assets/0A1D444013DA9E1178F2E33F32ADF646.svg"},"width":1920,"height":1080},"E8E4C64DCA94429DF555F18E4E4D4812":{"type":"texture","index":262,"assetRequest":{"type":"slide","state":"contents","slide":"A78F63D5-FDA3-4B1D-88CB-7B8DFFCEED2E"},"url":{"web":"assets/E8E4C64DCA94429DF555F18E4E4D4812.svg"},"width":808,"height":783},"3FC4E191D09E38E54370752BC487F9D1":{"type":"texture","index":265,"assetRequest":{"type":"slide","state":"incoming","slide":"EBAE7425-5FFF-4014-9BBB-D7D423995EB6"},"url":{"web":"assets/3FC4E191D09E38E54370752BC487F9D1.svg"},"width":1920,"height":1080},"6585F9B6F97A3390E639AC72FF627FF1":{"type":"texture","index":257,"assetRequest":{"type":"slide","state":"contents","slide":"A78F63D5-FDA3-4B1D-88CB-7B8DFFCEED2E"},"url":{"web":"assets/6585F9B6F97A3390E639AC72FF627FF1.svg"},"width":553,"height":51},"3BAAF9D671212E1C473F360CF3E06CEA":{"type":"texture","index":258,"assetRequest":{"type":"slide","state":"contents","slide":"A78F63D5-FDA3-4B1D-88CB-7B8DFFCEED2E"},"url":{"web":"assets/3BAAF9D671212E1C473F360CF3E06CEA.svg"},"width":816,"height":1451},"F0F3681DF24187C0DF5D256C9A571180":{"type":"texture","index":260,"assetRequest":{"type":"slide","state":"contents","slide":"A78F63D5-FDA3-4B1D-88CB-7B8DFFCEED2E"},"url":{"web":"assets/F0F3681DF24187C0DF5D256C9A571180.svg"},"width":220,"height":116},"floating_button.mov-0.0000-7.7500":{"type":"video","index":0,"assetRequest":{},"url":{"web":"assets/floating_button.mov-0.0000-7.7500.m4v","native":"assets/floating_button.mov-0.0000-7.7500.m4v"},"width":568,"height":1012},"C130C5AF60F64A39736A81295A6210DD":{"type":"texture","index":255,"assetRequest":{"type":"slide","state":"contents","slide":"A78F63D5-FDA3-4B1D-88CB-7B8DFFCEED2E"},"url":{"web":"assets/C130C5AF60F64A39736A81295A6210DD.svg"},"width":1920,"height":1080},"06890844A0F3F6A0E49E0017AC09A952":{"type":"texture","index":259,"assetRequest":{"type":"slide","state":"contents","slide":"A78F63D5-FDA3-4B1D-88CB-7B8DFFCEED2E"},"url":{"web":"assets/06890844A0F3F6A0E49E0017AC09A952.svg"},"width":1104,"height":910},"9719536B9E752E2CFD9C8372979B123D":{"type":"texture","index":256,"assetRequest":{"type":"slide","state":"contents","slide":"A78F63D5-FDA3-4B1D-88CB-7B8DFFCEED2E"},"url":{"web":"assets/9719536B9E752E2CFD9C8372979B123D.svg"},"width":1956,"height":10},"C849C809F413638AC928B3A95539CDD7":{"url":{"web":"assets/C849C809F413638AC928B3A95539CDD7.svg"},"height":1447.913818359375,"movie":"floating_button.mov-0.0000-7.7500","width":812.6629638671875,"type":"texture","assetRequest":{"byGlyphStyle":0,"deliveryStyle":0,"chunkIndex":1,"type":"chunk","chunkCount":1,"stageIndex":0,"stageCount":1},"index":263}},"events":[{"effects":[{"beginTime":0,"baseLayer":{"animations":[],"initialState":{"affineTransform":[1,0,0,1,0,0],"masksToBounds":false,"rotation":0,"scale":1,"position":{"pointX":1513.036804199219,"pointY":346.6463012695312},"width":812.6629638671875,"sublayerTransform":[1,0,0,0,0,1,0,0,0,0,1,0,0,0,0,1],"contentsRect":{"y":0,"x":0,"width":1,"height":1},"opacity":1,"edgeAntialiasingMask":251658240,"height":1447.913818359375,"hidden":false,"anchorPoint":{"pointX":0.5,"pointY":0.5}},"objectID":"8429950F-03F3-43C7-B773-1AD853C6E2E0","layers":[{"animations":[],"initialState":{"affineTransform":[1,0,0,1,0,0],"masksToBounds":false,"rotation":0,"scale":1,"position":{"pointX":-146.705322265625,"pointY":917.3106079101562},"width":812.6629638671875,"sublayerTransform":[1,0,0,0,0,1,0,0,0,0,1,-0.0003500791246677598,0,0,0,1],"contentsRect":{"y":0,"x":0,"width":1,"height":1},"opacity":1,"edgeAntialiasingMask":251658240,"height":1447.913818359375,"hidden":false,"anchorPoint":{"pointX":-0.1805241887331793,"pointY":0.6335395078621164}},"layers":[{"animations":[{"timeOffset":0,"beginTime":1e-100,"repeatCount":0,"animations":[{"timeOffset":0,"from":{"scalar":true},"beginTime":0,"repeatCount":0,"fillMode":"removed","property":"isPlaying","autoreverses":false,"duration":0.01,"to":{"scalar":true}},{"timeOffset":0,"from":{"scalar":false},"beginTime":0,"repeatCount":0,"fillMode":"removed","property":"hidden","autoreverses":false,"duration":0.01,"to":{"scalar":false}}],"fillMode":"both","autoreverses":false,"duration":0.01}],"layers":[],"initialState":{"affineTransform":[1,0,0,1,0,0],"masksToBounds":false,"rotation":0,"scale":1,"position":{"pointX":406.294677734375,"pointY":723.8106079101562},"width":816,"sublayerTransform":[1,0,0,0,0,1,0,0,0,0,1,0,0,0,0,1],"contentsRect":{"y":0,"x":0,"width":1,"height":1},"opacity":1,"edgeAntialiasingMask":0,"height":1451,"hidden":false,"anchorPoint":{"pointX":0.5,"pointY":0.5}},"texture":"3BAAF9D671212E1C473F360CF3E06CEA"}]}]},"effects":[{"beginTime":0,"baseLayer":{"animations":[],"initialState":{"affineTransform":[1,0,0,1,0,0],"masksToBounds":false,"rotation":0,"scale":1,"position":{"pointX":1513.036804199219,"pointY":346.6463012695312},"width":812.6629638671875,"sublayerTransform":[1,0,0,0,0,1,0,0,0,0,1,0,0,0,0,1],"contentsRect":{"y":0,"x":0,"width":1,"height":1},"opacity":1,"edgeAntialiasingMask":251658240,"height":1447.913818359375,"hidden":false,"anchorPoint":{"pointX":0.5,"pointY":0.5}},"objectID":"8429950F-03F3-43C7-B773-1AD853C6E2E0","layers":[{"animations":[],"layers":[],"initialState":{"affineTransform":[1,0,0,1,0,0],"masksToBounds":false,"rotation":0,"scale":1,"position":{"pointX":406.294677734375,"pointY":723.8106079101562},"width":816,"sublayerTransform":[1,0,0,0,0,1,0,0,0,0,1,0,0,0,0,1],"contentsRect":{"y":0,"x":0,"width":1,"height":1},"opacity":1,"edgeAntialiasingMask":0,"height":1451,"hidden":true,"anchorPoint":{"pointX":0.5,"pointY":0.5}},"texture":"3BAAF9D671212E1C473F360CF3E06CEA"},{"animations":[],"layers":[],"initialState":{"affineTransform":[1,0,0,1,0,0],"masksToBounds":false,"rotation":0,"scale":1,"position":{"pointX":406.3314819335938,"pointY":723.9569091796875},"width":812.6629638671875,"sublayerTransform":[1,0,0,0,0,1,0,0,0,0,1,0,0,0,0,1],"contentsRect":{"y":0,"x":0,"width":1,"height":1},"opacity":1,"edgeAntialiasingMask":251658240,"height":1447.913818359375,"hidden":false,"anchorPoint":{"pointX":0.5,"pointY":0.5}},"texture":"C849C809F413638AC928B3A95539CDD7"}]},"effects":[],"movie":{"volume":1,"isStreaming":false,"isAudioOnly":false,"endTime":7.75,"startTime":0,"asset":"floating_button.mov-0.0000-7.7500","loopMode":"looping"},"duration":0,"type":"buildIn","name":"renderMovie","objectID":"8429950F-03F3-43C7-B773-1AD853C6E2E0"}],"duration":0.01,"type":"buildIn","name":"apple:movie-start","objectID":"8429950F-03F3-43C7-B773-1AD853C6E2E0"}],"automaticPlay":true,"hyperlinks":[],"accessibility":[{"text":"Floating button menu","targetRectangle":{"y":34.04354953765869,"x":50.0625,"width":557.9640009834766,"height":65.80020141601562}},{"text":"Screen Shot 2018-03-31 at 11.48.34 AM.jpg","targetRectangle":{"y":43.21322727203369,"x":972.0763721466064,"width":805.8125,"height":780.4851902723312}},{"text":"Screen Shot 2018-03-31 at 11.12.41 AM.jpg","targetRectangle":{"y":136,"x":-5.915283203125,"width":1101.28125,"height":908}}],"baseLayer":{"animations":[],"initialState":{"affineTransform":[1,0,0,1,0,0],"masksToBounds":false,"rotation":0,"scale":1,"position":{"pointX":960,"pointY":540},"width":1920,"sublayerTransform":[1,0,0,0,0,1,0,0,0,0,1,0,0,0,0,1],"contentsRect":{"y":0,"x":0,"width":1,"height":1},"opacity":1,"edgeAntialiasingMask":251658240,"height":1080,"hidden":false,"anchorPoint":{"pointX":0.5,"pointY":0.5}},"layers":[{"animations":[],"initialState":{"affineTransform":[1,0,0,1,0,0],"masksToBounds":false,"rotation":0,"scale":1,"position":{"pointX":960,"pointY":540},"width":1920,"sublayerTransform":[1,0,0,0,0,1,0,0,0,0,1,0,0,0,0,1],"contentsRect":{"y":0,"x":0,"width":1,"height":1},"opacity":1,"edgeAntialiasingMask":251658240,"height":1080,"hidden":false,"anchorPoint":{"pointX":0.5,"pointY":0.5}},"layers":[{"animations":[],"initialState":{"affineTransform":[1,0,0,1,0,0],"masksToBounds":false,"rotation":0,"scale":1,"position":{"pointX":960,"pointY":540},"width":1920,"sublayerTransform":[1,0,0,0,0,1,0,0,0,0,1,0,0,0,0,1],"contentsRect":{"y":0,"x":0,"width":1,"height":1},"opacity":1,"edgeAntialiasingMask":251658240,"height":1080,"hidden":false,"anchorPoint":{"pointX":0.5,"pointY":0.5}},"layers":[{"animations":[],"layers":[],"initialState":{"affineTransform":[1,0,0,1,0,0],"masksToBounds":false,"rotation":0,"scale":1,"position":{"pointX":960,"pointY":540},"width":1920,"sublayerTransform":[1,0,0,0,0,1,0,0,0,0,1,0,0,0,0,1],"contentsRect":{"y":0,"x":0,"width":1,"height":1},"opacity":1,"edgeAntialiasingMask":0,"height":1080,"hidden":false,"anchorPoint":{"pointX":0.5,"pointY":0.5}},"texture":"C130C5AF60F64A39736A81295A6210DD"}]}]},{"animations":[],"initialState":{"affineTransform":[1,0,0,1,0,0],"masksToBounds":false,"rotation":0,"scale":1,"position":{"pointX":960,"pointY":540},"width":1920,"sublayerTransform":[1,0,0,0,0,1,0,0,0,0,1,0,0,0,0,1],"contentsRect":{"y":0,"x":0,"width":1,"height":1},"opacity":1,"edgeAntialiasingMask":251658240,"height":1080,"hidden":false,"anchorPoint":{"pointX":0.5,"pointY":0.5}},"layers":[{"animations":[],"initialState":{"affineTransform":[1,0,0,1,0,0],"masksToBounds":false,"rotation":0,"scale":1,"position":{"pointX":960.000030517578,"pointY":109.9710701073077},"width":1952.986978961727,"sublayerTransform":[1,0,0,0,0,1,0,0,0,0,1,0,0,0,0,1],"contentsRect":{"y":0,"x":0,"width":1,"height":1},"opacity":1,"edgeAntialiasingMask":251658240,"height":7.083541637861842,"hidden":false,"anchorPoint":{"pointX":0.5,"pointY":0.5}},"objectID":"7362567F-9457-4D65-8ED3-18ECBBB2944B","layers":[{"animations":[],"layers":[],"initialState":{"affineTransform":[1,0,0,1,0,0],"masksToBounds":false,"rotation":0,"scale":1,"position":{"pointX":976.4934589632855,"pointY":3.570700711623218},"width":1956,"sublayerTransform":[1,0,0,0,0,1,0,0,0,0,1,0,0,0,0,1],"contentsRect":{"y":0,"x":0,"width":1,"height":1},"opacity":1,"edgeAntialiasingMask":0,"height":10,"hidden":false,"anchorPoint":{"pointX":0.5,"pointY":0.5}},"texture":"9719536B9E752E2CFD9C8372979B123D"}]}]},{"animations":[],"initialState":{"affineTransform":[1,0,0,1,0,0],"masksToBounds":false,"rotation":0,"scale":1,"position":{"pointX":960,"pointY":540},"width":1920,"sublayerTransform":[1,0,0,0,0,1,0,0,0,0,1,0,0,0,0,1],"contentsRect":{"y":0,"x":0,"width":1,"height":1},"opacity":1,"edgeAntialiasingMask":251658240,"height":1080,"hidden":false,"anchorPoint":{"pointX":0.5,"pointY":0.5}},"layers":[{"animations":[],"initialState":{"affineTransform":[1,0,0,1,0,0],"masksToBounds":false,"rotation":0,"scale":1,"position":{"pointX":783.4687385559082,"pointY":66.94364976882935},"width":1478.062477111816,"sublayerTransform":[1,0,0,0,0,1,0,0,0,0,1,0,0,0,0,1],"contentsRect":{"y":0,"x":0,"width":1,"height":1},"opacity":1,"edgeAntialiasingMask":251658240,"height":77.05020046234131,"hidden":false,"anchorPoint":{"pointX":0.5,"pointY":0.5}},"objectID":"01B316AD-832B-4085-BFDC-D5A67920C405","layers":[{"animations":[],"layers":[],"initialState":{"affineTransform":[1,0,0,1,0,0],"masksToBounds":false,"rotation":0,"scale":1,"position":{"pointX":283.0625,"pointY":29.08145046234131},"width":553,"sublayerTransform":[1,0,0,0,0,1,0,0,0,0,1,0,0,0,0,1],"contentsRect":{"y":0,"x":0,"width":1,"height":1},"opacity":1,"edgeAntialiasingMask":0,"height":51,"hidden":false,"anchorPoint":{"pointX":0.5,"pointY":0.5}},"texture":"6585F9B6F97A3390E639AC72FF627FF1"}]}]},{"animations":[],"initialState":{"affineTransform":[1,0,0,1,0,0],"masksToBounds":false,"rotation":0,"scale":1,"position":{"pointX":960,"pointY":540},"width":1920,"sublayerTransform":[1,0,0,0,0,1,0,0,0,0,1,0,0,0,0,1],"contentsRect":{"y":0,"x":0,"width":1,"height":1},"opacity":1,"edgeAntialiasingMask":251658240,"height":1080,"hidden":false,"anchorPoint":{"pointX":0.5,"pointY":0.5}},"layers":[{"animations":[],"initialState":{"affineTransform":[1,0,0,1,0,0],"masksToBounds":false,"rotation":0,"scale":1,"position":{"pointX":1513.036804199219,"pointY":346.6463012695312},"width":812.6629638671875,"sublayerTransform":[1,0,0,0,0,1,0,0,0,0,1,0,0,0,0,1],"contentsRect":{"y":0,"x":0,"width":1,"height":1},"opacity":1,"edgeAntialiasingMask":251658240,"height":1447.913818359375,"hidden":false,"anchorPoint":{"pointX":0.5,"pointY":0.5}},"objectID":"8429950F-03F3-43C7-B773-1AD853C6E2E0","layers":[{"animations":[],"layers":[],"initialState":{"affineTransform":[1,0,0,1,0,0],"masksToBounds":false,"rotation":0,"scale":1,"position":{"pointX":406.294677734375,"pointY":723.8106079101562},"width":816,"sublayerTransform":[1,0,0,0,0,1,0,0,0,0,1,0,0,0,0,1],"contentsRect":{"y":0,"x":0,"width":1,"height":1},"opacity":1,"edgeAntialiasingMask":0,"height":1451,"hidden":false,"anchorPoint":{"pointX":0.5,"pointY":0.5}},"texture":"3BAAF9D671212E1C473F360CF3E06CEA"}]}]},{"animations":[],"initialState":{"affineTransform":[1,0,0,1,0,0],"masksToBounds":false,"rotation":0,"scale":1,"position":{"pointX":960,"pointY":540},"width":1920,"sublayerTransform":[1,0,0,0,0,1,0,0,0,0,1,0,0,0,0,1],"contentsRect":{"y":0,"x":0,"width":1,"height":1},"opacity":1,"edgeAntialiasingMask":251658240,"height":1080,"hidden":false,"anchorPoint":{"pointX":0.5,"pointY":0.5}},"layers":[{"animations":[],"initialState":{"affineTransform":[1,0,0,1,0,0],"masksToBounds":false,"rotation":0,"scale":1,"position":{"pointX":544.725341796875,"pointY":590},"width":1101.28125,"sublayerTransform":[1,0,0,0,0,1,0,0,0,0,1,0,0,0,0,1],"contentsRect":{"y":0,"x":0,"width":1,"height":1},"opacity":1,"edgeAntialiasingMask":251658240,"height":908,"hidden":false,"anchorPoint":{"pointX":0.5,"pointY":0.5}},"objectID":"74157115-0C04-4E95-AD9C-EFDE04BE6890","layers":[{"animations":[],"layers":[],"initialState":{"affineTransform":[1,0,0,1,0,0],"masksToBounds":false,"rotation":0,"scale":1,"position":{"pointX":550.915283203125,"pointY":454},"width":1104,"sublayerTransform":[1,0,0,0,0,1,0,0,0,0,1,0,0,0,0,1],"contentsRect":{"y":0,"x":0,"width":1,"height":1},"opacity":1,"edgeAntialiasingMask":0,"height":910,"hidden":false,"anchorPoint":{"pointX":0.5,"pointY":0.5}},"texture":"06890844A0F3F6A0E49E0017AC09A952"}]}]},{"animations":[],"initialState":{"affineTransform":[1,0,0,1,0,0],"masksToBounds":false,"rotation":0,"scale":1,"position":{"pointX":960,"pointY":540},"width":1920,"sublayerTransform":[1,0,0,0,0,1,0,0,0,0,1,0,0,0,0,1],"contentsRect":{"y":0,"x":0,"width":1,"height":1},"opacity":1,"edgeAntialiasingMask":251658240,"height":1080,"hidden":false,"anchorPoint":{"pointX":0.5,"pointY":0.5}},"layers":[{"animations":[],"initialState":{"affineTransform":[1,0,0,1,0,0],"masksToBounds":false,"rotation":0,"scale":1,"position":{"pointX":875.1555635226921,"pointY":634.8269007417406},"width":217.2298666621969,"sublayerTransform":[1,0,0,0,0,1,0,0,0,0,1,0,0,0,0,1],"contentsRect":{"y":0,"x":0,"width":1,"height":1},"opacity":1,"edgeAntialiasingMask":251658240,"height":112.8678452531303,"hidden":false,"anchorPoint":{"pointX":0.5,"pointY":0.5}},"objectID":"D97AD218-D885-48FD-B7B2-7B42ECC9A1A4","layers":[{"animations":[],"layers":[],"initialState":{"affineTransform":[1,0,0,1,0,0],"masksToBounds":false,"rotation":0,"scale":1,"position":{"pointX":108.4593698084063,"pointY":56.60702188482458},"width":220,"sublayerTransform":[1,0,0,0,0,1,0,0,0,0,1,0,0,0,0,1],"contentsRect":{"y":0,"x":0,"width":1,"height":1},"opacity":1,"edgeAntialiasingMask":0,"height":116,"hidden":false,"anchorPoint":{"pointX":0.5,"pointY":0.5}},"texture":"F0F3681DF24187C0DF5D256C9A571180"}]}]},{"animations":[],"initialState":{"affineTransform":[1,0,0,1,0,0],"masksToBounds":false,"rotation":0,"scale":1,"position":{"pointX":960,"pointY":540},"width":1920,"sublayerTransform":[1,0,0,0,0,1,0,0,0,0,1,0,0,0,0,1],"contentsRect":{"y":0,"x":0,"width":1,"height":1},"opacity":1,"edgeAntialiasingMask":251658240,"height":1080,"hidden":false,"anchorPoint":{"pointX":0.5,"pointY":0.5}},"layers":[{"animations":[],"initialState":{"affineTransform":[1,0,0,1,0,0],"masksToBounds":false,"rotation":0,"scale":1,"position":{"pointX":516.9141941070557,"pointY":712.7235818505287},"width":745.2641487121582,"sublayerTransform":[1,0,0,0,0,1,0,0,0,0,1,0,0,0,0,1],"contentsRect":{"y":0,"x":0,"width":1,"height":1},"opacity":0.4000000059604645,"edgeAntialiasingMask":251658240,"height":41.49403870105743,"hidden":false,"anchorPoint":{"pointX":0.5,"pointY":0.5}},"objectID":"19A54B44-A8F1-43E8-8549-7AF5182D09F6","layers":[{"animations":[],"layers":[],"initialState":{"affineTransform":[1,0,0,1,0,0],"masksToBounds":false,"rotation":0,"scale":1,"position":{"pointX":372.7178802490234,"pointY":20.5234375},"width":748,"sublayerTransform":[1,0,0,0,0,1,0,0,0,0,1,0,0,0,0,1],"contentsRect":{"y":0,"x":0,"width":1,"height":1},"opacity":1,"edgeAntialiasingMask":0,"height":45,"hidden":false,"anchorPoint":{"pointX":0.5,"pointY":0.5}},"texture":"93C48EF3C6BA71FE6A02681D2F3B7885"}]}]},{"animations":[],"initialState":{"affineTransform":[1,0,0,1,0,0],"masksToBounds":false,"rotation":0,"scale":1,"position":{"pointX":960,"pointY":540},"width":1920,"sublayerTransform":[1,0,0,0,0,1,0,0,0,0,1,0,0,0,0,1],"contentsRect":{"y":0,"x":0,"width":1,"height":1},"opacity":1,"edgeAntialiasingMask":251658240,"height":1080,"hidden":false,"anchorPoint":{"pointX":0.5,"pointY":0.5}},"layers":[{"animations":[],"initialState":{"affineTransform":[1,0,0,1,0,0],"masksToBounds":false,"rotation":0,"scale":1,"position":{"pointX":1374.982622146606,"pointY":433.4558224081993},"width":805.8125,"sublayerTransform":[1,0,0,0,0,1,0,0,0,0,1,0,0,0,0,1],"contentsRect":{"y":0,"x":0,"width":1,"height":1},"opacity":1,"edgeAntialiasingMask":251658240,"height":780.4851902723312,"hidden":false,"anchorPoint":{"pointX":0.5,"pointY":0.5}},"objectID":"7B7CA9B3-7118-44D7-BDD0-80FF6FEB2C16","layers":[{"animations":[],"layers":[],"initialState":{"affineTransform":[1,0,0,1,0,0],"masksToBounds":false,"rotation":0,"scale":1,"position":{"pointX":402.9236278533936,"pointY":390.2867727279663},"width":808,"sublayerTransform":[1,0,0,0,0,1,0,0,0,0,1,0,0,0,0,1],"contentsRect":{"y":0,"x":0,"width":1,"height":1},"opacity":1,"edgeAntialiasingMask":0,"height":783,"hidden":false,"anchorPoint":{"pointX":0.5,"pointY":0.5}},"texture":"E8E4C64DCA94429DF555F18E4E4D4812"}]}]}]}},{"effects":[{"beginTime":0,"baseLayer":{"animations":[],"initialState":{"affineTransform":[1,0,0,1,0,0],"masksToBounds":false,"rotation":0,"scale":1,"position":{"pointX":960,"pointY":540},"width":1920,"sublayerTransform":[1,0,0,0,0,1,0,0,0,0,1,0,0,0,0,1],"contentsRect":{"y":0,"x":0,"width":1,"height":1},"opacity":1,"edgeAntialiasingMask":251658240,"height":1080,"hidden":false,"anchorPoint":{"pointX":0.5,"pointY":0.5}},"objectID":"0","layers":[{"animations":[],"initialState":{"affineTransform":[1,0,0,1,0,0],"masksToBounds":false,"rotation":0,"scale":1,"position":{"pointX":960,"pointY":540},"width":1920,"sublayerTransform":[1,0,0,0,0,1,0,0,0,0,1,-0.0003500791246677598,0,0,0,1],"contentsRect":{"y":0,"x":0,"width":1,"height":1},"opacity":1,"edgeAntialiasingMask":251658240,"height":1080,"hidden":false,"anchorPoint":{"pointX":0.5,"pointY":0.5}},"layers":[{"animations":[],"layers":[],"initialState":{"affineTransform":[1,0,0,1,0,0],"masksToBounds":false,"rotation":0,"scale":1,"position":{"pointX":960,"pointY":540},"width":1920,"sublayerTransform":[1,0,0,0,0,1,0,0,0,0,1,0,0,0,0,1],"contentsRect":{"y":0,"x":0,"width":1,"height":1},"opacity":1,"edgeAntialiasingMask":0,"height":1080,"hidden":false,"anchorPoint":{"pointX":0.5,"pointY":0.5}},"texture":"3FC4E191D09E38E54370752BC487F9D1"},{"animations":[{"timeOffset":0,"from":{"scalar":false},"beginTime":0,"repeatCount":0,"fillMode":"both","property":"hidden","autoreverses":false,"duration":0.01,"to":{"scalar":true}}],"layers":[],"initialState":{"affineTransform":[1,0,0,1,0,0],"masksToBounds":false,"rotation":0,"scale":1,"position":{"pointX":960,"pointY":540},"width":1920,"sublayerTransform":[1,0,0,0,0,1,0,0,0,0,1,0,0,0,0,1],"contentsRect":{"y":0,"x":0,"width":1,"height":1},"opacity":1,"edgeAntialiasingMask":0,"height":1080,"hidden":false,"anchorPoint":{"pointX":0.5,"pointY":0.5}},"texture":"0A1D444013DA9E1178F2E33F32ADF646"}]}]},"effects":[],"duration":0.01,"type":"transition","name":"none","objectID":"0"}],"automaticPlay":false,"hyperlinks":[],"accessibility":[{"text":"Floating button menu","targetRectangle":{"y":34.04354953765869,"x":50.0625,"width":557.9640009834766,"height":65.80020141601562}},{"text":"Screen Shot 2018-03-31 at 11.48.34 AM.jpg","targetRectangle":{"y":43.21322727203369,"x":972.0763721466064,"width":805.8125,"height":780.4851902723312}},{"text":"Screen Shot 2018-03-31 at 11.12.41 AM.jpg","targetRectangle":{"y":136,"x":-5.915283203125,"width":1101.28125,"height":908}}],"baseLayer":{"animations":[],"initialState":{"affineTransform":[1,0,0,1,0,0],"masksToBounds":false,"rotation":0,"scale":1,"position":{"pointX":960,"pointY":540},"width":1920,"sublayerTransform":[1,0,0,0,0,1,0,0,0,0,1,0,0,0,0,1],"contentsRect":{"y":0,"x":0,"width":1,"height":1},"opacity":1,"edgeAntialiasingMask":251658240,"height":1080,"hidden":false,"anchorPoint":{"pointX":0.5,"pointY":0.5}},"objectID":"0","layers":[{"animations":[],"initialState":{"affineTransform":[1,0,0,1,0,0],"masksToBounds":false,"rotation":0,"scale":1,"position":{"pointX":960,"pointY":540},"width":1920,"sublayerTransform":[1,0,0,0,0,1,0,0,0,0,1,-0.0003500791246677598,0,0,0,1],"contentsRect":{"y":0,"x":0,"width":1,"height":1},"opacity":1,"edgeAntialiasingMask":251658240,"height":1080,"hidden":false,"anchorPoint":{"pointX":0.5,"pointY":0.5}},"layers":[{"animations":[],"layers":[],"initialState":{"affineTransform":[1,0,0,1,0,0],"masksToBounds":false,"rotation":0,"scale":1,"position":{"pointX":960,"pointY":540},"width":1920,"sublayerTransform":[1,0,0,0,0,1,0,0,0,0,1,0,0,0,0,1],"contentsRect":{"y":0,"x":0,"width":1,"height":1},"opacity":1,"edgeAntialiasingMask":0,"height":1080,"hidden":false,"anchorPoint":{"pointX":0.5,"pointY":0.5}},"texture":"0A1D444013DA9E1178F2E33F32ADF646"}]}]}}]}